sr_vulkan_model_realcugan/__init__.py
sr_vulkan_model_realcugan/hook-sr_vulkan_model_realcugan.py
sr_vulkan_model_realcugan/models/REALCUGAN_PRO_UP2X.bin
sr_vulkan_model_realcugan/models/REALCUGAN_PRO_UP2X.param
sr_vulkan_model_realcugan/models/REALCUGAN_PRO_UP2X_CONSERVATIVE.bin
sr_vulkan_model_realcugan/models/REALCUGAN_PRO_UP2X_CONSERVATIVE.param
sr_vulkan_model_realcugan/models/REALCUGAN_PRO_UP2X_DENOISE3X.bin
sr_vulkan_model_realcugan/models/REALCUGAN_PRO_UP2X_DENOISE3X.param
sr_vulkan_model_realcugan/models/REALCUGAN_PRO_UP3X.bin
sr_vulkan_model_realcugan/models/REALCUGAN_PRO_UP3X.param
sr_vulkan_model_realcugan/models/REALCUGAN_PRO_UP3X_CONSERVATIVE.bin
sr_vulkan_model_realcugan/models/REALCUGAN_PRO_UP3X_CONSERVATIVE.param
sr_vulkan_model_realcugan/models/REALCUGAN_PRO_UP3X_DENOISE3X.bin
sr_vulkan_model_realcugan/models/REALCUGAN_PRO_UP3X_DENOISE3X.param
sr_vulkan_model_realcugan/models/REALCUGAN_SE_UP2X.bin
sr_vulkan_model_realcugan/models/REALCUGAN_SE_UP2X.param
sr_vulkan_model_realcugan/models/REALCUGAN_SE_UP2X_CONSERVATIVE.bin
sr_vulkan_model_realcugan/models/REALCUGAN_SE_UP2X_CONSERVATIVE.param
sr_vulkan_model_realcugan/models/REALCUGAN_SE_UP2X_DENOISE1X.bin
sr_vulkan_model_realcugan/models/REALCUGAN_SE_UP2X_DENOISE1X.param
sr_vulkan_model_realcugan/models/REALCUGAN_SE_UP2X_DENOISE2X.bin
sr_vulkan_model_realcugan/models/REALCUGAN_SE_UP2X_DENOISE2X.param
sr_vulkan_model_realcugan/models/REALCUGAN_SE_UP2X_DENOISE3X.bin
sr_vulkan_model_realcugan/models/REALCUGAN_SE_UP2X_DENOISE3X.param
sr_vulkan_model_realcugan/models/REALCUGAN_SE_UP3X.bin
sr_vulkan_model_realcugan/models/REALCUGAN_SE_UP3X.param
sr_vulkan_model_realcugan/models/REALCUGAN_SE_UP3X_CONSERVATIVE.bin
sr_vulkan_model_realcugan/models/REALCUGAN_SE_UP3X_CONSERVATIVE.param
sr_vulkan_model_realcugan/models/REALCUGAN_SE_UP3X_DENOISE3X.bin
sr_vulkan_model_realcugan/models/REALCUGAN_SE_UP3X_DENOISE3X.param
sr_vulkan_model_realcugan/models/REALCUGAN_SE_UP4X.bin
sr_vulkan_model_realcugan-1.0.1.dist-info/METADATA
sr_vulkan_model_realcugan-1.0.1.dist-info/WHEEL
sr_vulkan_model_realcugan-1.0.1.dist-info/entry_points.txt
sr_vulkan_model_realcugan-1.0.1.dist-info/top_level.txt
sr_vulkan_model_realcugan-1.0.1.dist-info/RECORD
