Metadata-Version: 2.1
Name: sr-vulkan-model-realcugan
Version: 1.0.1
Summary: sr_vulkan realcugan model
Home-page: http://github.com/tonquer/sr_vulkan
Author: tonquer
Author-email: tonquer@qq.com
License: MIT
Platform: UNKNOWN
Classifier: Programming Language :: Python :: 3
Classifier: License :: OSI Approved :: MIT License
Classifier: Operating System :: OS Independent
